{
	"T": {
		"is_attr": null,
		"input_order": -1,
		"default": null,
		"is_mid": true,
		"name": "T",
		"type": "type",
		"enum": null,
		"optional": null
	},
	"Tshift": {
		"is_attr": null,
		"input_order": -1,
		"default": null,
		"is_mid": true,
		"name": "Tshift",
		"type": "type",
		"enum": [
			"int32",
			"int64"
		],
		"optional": null
	},
	"Taxis": {
		"is_attr": null,
		"input_order": -1,
		"default": null,
		"is_mid": true,
		"name": "Taxis",
		"type": "type",
		"enum": [
			"int32",
			"int64"
		],
		"optional": null
	},
	"input": {
		"input_order": 0,
		"is_attr": null,
		"default": null,
		"is_mid": null,
		"name": "input",
		"type": "tensor",
		"value": null,
		"shape": null,
		"ndim": null,
		"max_ndim": null,
		"min_ndim": null,
		"dtype": "&T.value",
		"optional": null
	},
	"shift": {
		"input_order": 1,
		"is_attr": null,
		"default": null,
		"is_mid": null,
		"name": "shift",
		"type": "tensor",
		"value": null,
		"shape": null,
		"ndim": null,
		"max_ndim": null,
		"min_ndim": null,
		"dtype": "&Tshift.value",
		"optional": null
	},
	"axis": {
		"input_order": 2,
		"is_attr": null,
		"default": null,
		"is_mid": null,
		"name": "axis",
		"type": "tensor",
		"value": null,
		"shape": null,
		"ndim": null,
		"max_ndim": null,
		"min_ndim": null,
		"dtype": "&Taxis.value",
		"optional": null
	}
}