{
	"input": {
		"optional": false,
		"name": "input",
		"type": "tensor",
		"input_order": 0,
		"dtype": "&T.value"
	},
	"dim": {
		"optional": false,
		"name": "dim",
		"type": "int",
		"input_order": 1,
		"max": 6,
		"min": -6
	},
	"start": {
		"optional": false,
		"name": "start",
		"type": "int",
		"input_order": 2
	},
	"length": {
		"optional": false,
		"name": "length",
		"type": "int",
		"input_order": 3
	},
	"T": {
		"name": "T",
		"is_mid": true,
		"type": "type",
		"input_order": -1,
		"enum": [
			"int8",
			"int16",
			"int32",
			"int64",
			"uint8",
			"uint16",
			"uint32",
			"uint64",
			"half",
			"bfloat16",
			"float16",
			"float32",
			"float64",
			"complex32",
			"complex64"
		]
	}
}