{
	"anchor": {
		"input_order": 0,
		"is_attr": null,
		"default": null,
		"is_mid": null,
		"name": "anchor",
		"type": "tensor",
		"value": null,
		"shape": null,
		"ndim": null,
		"max_ndim": null,
		"min_ndim": null,
		"dtype": "&T.value",
		"optional": false
	},
	"positive": {
		"input_order": 1,
		"is_attr": null,
		"default": null,
		"is_mid": null,
		"name": "positive",
		"type": "tensor",
		"value": null,
		"shape": null,
		"ndim": null,
		"max_ndim": null,
		"min_ndim": null,
		"dtype": "&T.value",
		"optional": false
	},
	"negative": {
		"input_order": 2,
		"is_attr": null,
		"default": null,
		"is_mid": null,
		"name": "negative",
		"type": "tensor",
		"value": null,
		"shape": null,
		"ndim": null,
		"max_ndim": null,
		"min_ndim": null,
		"dtype": "&T.value",
		"optional": false
	},
	"margin": {
		"is_attr": null,
		"input_order": 3,
		"default": 1.0,
		"is_mid": null,
		"name": "margin",
		"type": "float",
		"max": null,
		"min": null,
		"value": null,
		"optional": false
	},
	"p": {
		"is_attr": null,
		"input_order": 4,
		"default": 2.0,
		"is_mid": null,
		"name": "p",
		"type": "float",
		"max": null,
		"min": null,
		"value": null,
		"optional": false
	},
	"eps": {
		"is_attr": null,
		"input_order": 5,
		"default": 1e-06,
		"is_mid": null,
		"name": "eps",
		"type": "float",
		"max": null,
		"min": null,
		"value": null,
		"optional": false
	},
	"swap": {
		"is_attr": null,
		"input_order": 6,
		"default": "False",
		"is_mid": null,
		"name": "swap",
		"type": "bool",
		"value": null,
		"optional": false
	},
	"reduction": {
		"is_attr": null,
		"input_order": 7,
		"default": 1,
		"is_mid": null,
		"name": "reduction",
		"type": "int",
		"max": null,
		"min": null,
		"value": null,
		"enum": [
			0,
			1,
			2
		],
		"optional": false
	},
	"T": {
		"is_attr": null,
		"input_order": -1,
		"default": null,
		"is_mid": true,
		"name": "T",
		"type": "type",
		"enum": [
			"int8",
			"int16",
			"int32",
			"int64",
			"uint8",
			"uint16",
			"uint32",
			"uint64",
			"half",
			"bfloat16",
			"float16",
			"float32",
			"float64",
			"complex32",
			"complex64"
		],
		"optional": null
	}
}